posql_simple/__init__.py
posql_simple/test.py
posql_simple/w_out_sql.py
poslq_simple-0.2.1.dist-info/LICENSE
poslq_simple-0.2.1.dist-info/METADATA
poslq_simple-0.2.1.dist-info/WHEEL
poslq_simple-0.2.1.dist-info/top_level.txt
poslq_simple-0.2.1.dist-info/RECORD
