Metadata-Version: 2.1
Name: poslq-simple
Version: 0.2.1
Summary: A simple nosql json storage for small projects.
Author-email: enyos <lebedevhh@outlook.fr>
Project-URL: Homepage, https://github.com/enyoos/nosql
Project-URL: Bug Tracker, https://github.com/enyoos/nosql/issues
Classifier: Programming Language :: Python :: 3
Classifier: License :: OSI Approved :: MIT License
Classifier: Operating System :: OS Independent
Requires-Python: >=3.7
License-File: LICENSE
